sudothink/__init__.py
sudothink/assistant.py
sudothink/cli.py
sudothink/config.py
sudothink/setup.py
sudothink-1.0.4.dist-info/licenses/LICENSE
sudothink-1.0.4.dist-info/METADATA
sudothink-1.0.4.dist-info/WHEEL
sudothink-1.0.4.dist-info/entry_points.txt
sudothink-1.0.4.dist-info/top_level.txt
sudothink-1.0.4.dist-info/RECORD
