Metadata-Version: 2.4
Name: sudothink
Version: 1.0.4
Summary: An intelligent terminal assistant that uses OpenAI's GPT-4 to help with complex shell tasks
Home-page: https://github.com/vusallyv/sudothink
Author: Vusal Abdullayev
Author-email: Vusal Abdullayev <abdulla.vusal.3@gmail.com>
Maintainer-email: Vusal Abdullayev <abdulla.vusal.3@gmail.com>
License: MIT
Project-URL: Homepage, https://github.com/vusallyv/sudothink
Project-URL: Documentation, https://github.com/vusallyv/sudothink#readme
Project-URL: Repository, https://github.com/vusallyv/sudothink
Project-URL: Bug Tracker, https://github.com/vusallyv/sudothink/issues
Keywords: terminal,ai,openai,shell,automation,productivity
Classifier: Development Status :: 4 - Beta
Classifier: Intended Audience :: Developers
Classifier: Intended Audience :: System Administrators
Classifier: License :: OSI Approved :: MIT License
Classifier: Operating System :: OS Independent
Classifier: Programming Language :: Python :: 3
Classifier: Programming Language :: Python :: 3.7
Classifier: Programming Language :: Python :: 3.8
Classifier: Programming Language :: Python :: 3.9
Classifier: Programming Language :: Python :: 3.10
Classifier: Programming Language :: Python :: 3.11
Classifier: Topic :: System :: Systems Administration
Classifier: Topic :: Utilities
Requires-Python: >=3.7
License-File: LICENSE
Requires-Dist: openai>=1.0.0
Requires-Dist: requests>=2.25.0
Provides-Extra: dev
Requires-Dist: pytest>=6.0; extra == "dev"
Requires-Dist: black>=21.0; extra == "dev"
Requires-Dist: flake8>=3.8; extra == "dev"
Requires-Dist: mypy>=0.800; extra == "dev"
Dynamic: author
Dynamic: home-page
Dynamic: license-file
Dynamic: requires-python
